Metadata-Version: 2.0
Name: caar
Version: 5.0.0b6
Summary: Accelerating analysis of time stamped sensor observations and cycling device operations.
Home-page: http://github.com/nickpowersys/CaaR/
Author: Nicholas A. Brown
Author-email: nbprofessional@gmail.com
License: BSD 3-Clause License
Platform: any
Classifier: Development Status :: 4 - Beta
Classifier: Intended Audience :: Science/Research
Classifier: License :: OSI Approved :: BSD License
Classifier: Natural Language :: English
Classifier: Operating System :: MacOS :: MacOS X
Classifier: Operating System :: Microsoft :: Windows
Classifier: Operating System :: POSIX :: Linux
Classifier: Programming Language :: Python :: 2.7
Classifier: Programming Language :: Python :: 3.4
Classifier: Programming Language :: Python :: 3.5
Classifier: Topic :: Scientific/Engineering :: Information Analysis
Classifier: Topic :: Software Development :: Libraries :: Python Modules
Requires-Dist: configparser
Requires-Dist: future
Requires-Dist: numpy
Requires-Dist: pandas
Provides-Extra: testing
Requires-Dist: pytest; extra == 'testing'
